[
  {
    "ContainingType": "clinic.Controllers.AccountController",
    "Method": "Login",
    "RelativePath": "api/Account/Login",
    "HttpMethod": "POST",
    "IsController": true,
    "Order": 0,
    "Parameters": [
      {
        "Name": "loginUserDTO",
        "Type": "clinic.DTOs.loginUserDTO",
        "IsRequired": true
      }
    ],
    "ReturnTypes": [],
    "EndpointName": "Login"
  },
  {
    "ContainingType": "clinic.Controllers.AccountController",
    "Method": "Add",
    "RelativePath": "api/Account/Register",
    "HttpMethod": "POST",
    "IsController": true,
    "Order": 0,
    "Parameters": [
      {
        "Name": "accountDTO",
        "Type": "clinic.DTOs.AccountDTO",
        "IsRequired": true
      }
    ],
    "ReturnTypes": [],
    "EndpointName": "Register"
  },
  {
    "ContainingType": "clinic.Controllers.PatientsController",
    "Method": "Create",
    "RelativePath": "api/Patients/Create",
    "HttpMethod": "POST",
    "IsController": true,
    "Order": 0,
    "Parameters": [
      {
        "Name": "patientDto",
        "Type": "clinic.DTOs.PatientDto",
        "IsRequired": true
      }
    ],
    "ReturnTypes": []
  },
  {
    "ContainingType": "clinic.Controllers.PatientsController",
    "Method": "Delete",
    "RelativePath": "api/Patients/Delete",
    "HttpMethod": "DELETE",
    "IsController": true,
    "Order": 0,
    "Parameters": [
      {
        "Name": "id",
        "Type": "System.Int32",
        "IsRequired": false
      }
    ],
    "ReturnTypes": []
  },
  {
    "ContainingType": "clinic.Controllers.PatientsController",
    "Method": "Edit",
    "RelativePath": "api/Patients/Edit",
    "HttpMethod": "PUT",
    "IsController": true,
    "Order": 0,
    "Parameters": [
      {
        "Name": "Id",
        "Type": "System.Int32",
        "IsRequired": false
      },
      {
        "Name": "patientDto",
        "Type": "clinic.DTOs.PatientDto",
        "IsRequired": true
      }
    ],
    "ReturnTypes": []
  },
  {
    "ContainingType": "clinic.Controllers.PatientsController",
    "Method": "Show",
    "RelativePath": "api/Patients/Show",
    "HttpMethod": "GET",
    "IsController": true,
    "Order": 0,
    "Parameters": [],
    "ReturnTypes": [
      {
        "Type": "System.Collections.Generic.IEnumerable\u00601[[clinic.DTOs.PatientDto, ClinicManagement, Version=1.0.0.0, Culture=neutral, PublicKeyToken=null]]",
        "MediaTypes": [
          "text/plain",
          "application/json",
          "text/json"
        ],
        "StatusCode": 200
      }
    ]
  },
  {
    "ContainingType": "clinic.Controllers.AppointmentsController",
    "Method": "Create",
    "RelativePath": "Appointments/Create",
    "HttpMethod": "POST",
    "IsController": true,
    "Order": 0,
    "Parameters": [
      {
        "Name": "appointmentDto",
        "Type": "clinic.DTOs.AppointmentDto",
        "IsRequired": true
      }
    ],
    "ReturnTypes": []
  },
  {
    "ContainingType": "clinic.Controllers.AppointmentsController",
    "Method": "Delete",
    "RelativePath": "Appointments/Delete",
    "HttpMethod": "DELETE",
    "IsController": true,
    "Order": 0,
    "Parameters": [
      {
        "Name": "id",
        "Type": "System.Int32",
        "IsRequired": false
      }
    ],
    "ReturnTypes": []
  },
  {
    "ContainingType": "clinic.Controllers.AppointmentsController",
    "Method": "Show",
    "RelativePath": "Appointments/Show",
    "HttpMethod": "GET",
    "IsController": true,
    "Order": 0,
    "Parameters": [
      {
        "Name": "patientId",
        "Type": "System.Nullable\u00601[[System.Int32, System.Private.CoreLib, Version=8.0.0.0, Culture=neutral, PublicKeyToken=7cec85d7bea7798e]]",
        "IsRequired": false
      },
      {
        "Name": "doctorId",
        "Type": "System.Nullable\u00601[[System.Int32, System.Private.CoreLib, Version=8.0.0.0, Culture=neutral, PublicKeyToken=7cec85d7bea7798e]]",
        "IsRequired": false
      }
    ],
    "ReturnTypes": []
  },
  {
    "ContainingType": "clinic.Controllers.AppointmentsController",
    "Method": "Update",
    "RelativePath": "Appointments/Update",
    "HttpMethod": "PUT",
    "IsController": true,
    "Order": 0,
    "Parameters": [
      {
        "Name": "id",
        "Type": "System.Int32",
        "IsRequired": false
      },
      {
        "Name": "appointmentDto",
        "Type": "clinic.DTOs.AppointmentDto",
        "IsRequired": true
      }
    ],
    "ReturnTypes": []
  },
  {
    "ContainingType": "clinic.Controllers.DoctorsController",
    "Method": "Create",
    "RelativePath": "Doctors/Create",
    "HttpMethod": "POST",
    "IsController": true,
    "Order": 0,
    "Parameters": [
      {
        "Name": "doctorDto",
        "Type": "clinic.DTOs.DoctorDto",
        "IsRequired": true
      }
    ],
    "ReturnTypes": []
  },
  {
    "ContainingType": "clinic.Controllers.DoctorsController",
    "Method": "Delete",
    "RelativePath": "Doctors/Delete",
    "HttpMethod": "DELETE",
    "IsController": true,
    "Order": 0,
    "Parameters": [
      {
        "Name": "id",
        "Type": "System.Int32",
        "IsRequired": false
      }
    ],
    "ReturnTypes": []
  },
  {
    "ContainingType": "clinic.Controllers.DoctorsController",
    "Method": "Edit",
    "RelativePath": "Doctors/Edit",
    "HttpMethod": "PUT",
    "IsController": true,
    "Order": 0,
    "Parameters": [
      {
        "Name": "Id",
        "Type": "System.Int32",
        "IsRequired": false
      },
      {
        "Name": "doctorDto",
        "Type": "clinic.DTOs.DoctorDto",
        "IsRequired": true
      }
    ],
    "ReturnTypes": []
  },
  {
    "ContainingType": "clinic.Controllers.DoctorsController",
    "Method": "Show",
    "RelativePath": "Doctors/Show",
    "HttpMethod": "GET",
    "IsController": true,
    "Order": 0,
    "Parameters": [],
    "ReturnTypes": [
      {
        "Type": "System.Collections.Generic.List\u00601[[clinic.DTOs.DoctorDto, ClinicManagement, Version=1.0.0.0, Culture=neutral, PublicKeyToken=null]]",
        "MediaTypes": [
          "text/plain",
          "application/json",
          "text/json"
        ],
        "StatusCode": 200
      }
    ]
  }
]